brainlamp_toolbox/__init__.py
brainlamp_toolbox/essay/__init__.py
brainlamp_toolbox/essay/model.py
brainlamp_toolbox/essay/utils.py
brainlamp_toolbox/text/__init__.py
brainlamp_toolbox/text/paragraph.py
brainlamp_toolbox-0.1.3.dist-info/DESCRIPTION.rst
brainlamp_toolbox-0.1.3.dist-info/METADATA
brainlamp_toolbox-0.1.3.dist-info/RECORD
brainlamp_toolbox-0.1.3.dist-info/WHEEL
brainlamp_toolbox-0.1.3.dist-info/metadata.json
brainlamp_toolbox-0.1.3.dist-info/top_level.txt
