Metadata-Version: 2.0
Name: brainlamp-toolbox
Version: 0.1.3
Summary: Toolbox for Brain Lamp project
Home-page: http://github.com/brainlamp/brainlamp-toolbox
Author: Brain Lamp
Author-email: brainlamp18@gmail.com
License: BSD
Keywords: school,big data,machine learning,artificial inteligence
Platform: UNKNOWN
Classifier: Development Status :: 4 - Beta
Classifier: Intended Audience :: Science/Research
Classifier: License :: OSI Approved :: BSD License
Classifier: Programming Language :: Python :: 3.6
Classifier: Topic :: Utilities
Requires-Python: >=3
Requires-Dist: nltk (==3.2.5)
